deface/__init__.py
deface/_version.py
deface/centerface.onnx
deface/centerface.py
deface/deface.py
deface-1.5.0.dist-info/LICENSE
deface-1.5.0.dist-info/METADATA
deface-1.5.0.dist-info/WHEEL
deface-1.5.0.dist-info/entry_points.txt
deface-1.5.0.dist-info/top_level.txt
deface-1.5.0.dist-info/RECORD
