Metadata-Version: 2.1
Name: deface
Version: 1.5.0
Summary: Video anonymization by face detection
License: MIT License
Project-URL: repository, https://github.com/ORB-HD/deface
Classifier: Programming Language :: Python :: 3
Classifier: License :: OSI Approved :: MIT License
Classifier: Topic :: Scientific/Engineering :: Image Processing
Classifier: Topic :: Scientific/Engineering :: Image Recognition
Requires-Python: >=3.8
License-File: LICENSE
Requires-Dist: imageio>=2.25
Requires-Dist: imageio-ffmpeg>=0.4.6
Requires-Dist: numpy
Requires-Dist: tqdm
Requires-Dist: scikit-image
Requires-Dist: opencv-python
Provides-Extra: cuda
Requires-Dist: onnx; extra == "cuda"
Requires-Dist: onnxruntime-cuda; extra == "cuda"
Provides-Extra: directml
Requires-Dist: onnx; extra == "directml"
Requires-Dist: onnxruntime-directml; extra == "directml"
Provides-Extra: openvino
Requires-Dist: onnx; extra == "openvino"
Requires-Dist: onnxruntime-openvino; extra == "openvino"
